README.md
pyproject.toml
setup.py
examples/__init__.py
examples/http_sender.py
examples/redis_sender.py
examples/sequence.py
flow/__init__.py
flow/flowchart.py
flow/httpsender.py
flow/redis_sender.py
flow/sender.py
flow/sequence.py
flow_diagrams.egg-info/PKG-INFO
flow_diagrams.egg-info/SOURCES.txt
flow_diagrams.egg-info/dependency_links.txt
flow_diagrams.egg-info/top_level.txt