Metadata-Version: 2.4
Name: flow-diagrams
Version: 0.1.0
Summary: Client library for creating Mermaid diagrams
Requires: redis
Requires-Python: >=3.7
Dynamic: requires
Dynamic: requires-python
Dynamic: summary
